eelsmapper/__init__.py
eelsmapper/pipeline.py
eelsmapper/analysis/__init__.py
eelsmapper/analysis/mutual_info.py
eelsmapper/analysis/vector_quant.py
eelsmapper/clustering/__init__.py
eelsmapper/clustering/kmeans.py
eelsmapper/embedding/__init__.py
eelsmapper/embedding/tsne.py
eelsmapper/preprocessing/__init__.py
eelsmapper/preprocessing/pca_denoising.py
eelsmapper/visualization/__init__.py
eelsmapper/visualization/plot.py
eelsmapper-0.2.4.dist-info/METADATA
eelsmapper-0.2.4.dist-info/WHEEL
eelsmapper-0.2.4.dist-info/top_level.txt
eelsmapper-0.2.4.dist-info/RECORD
