Metadata-Version: 2.4
Name: eelsmapper
Version: 0.2.4
Summary: Data-driven analysis pipeline for STEM-EELS spectra. See project at [https://zhenyuan992.github.io/eelsmapper](https://zhenyuan992.github.io/eelsmapper)
Author: Yeo Zhen Yuan
Author-email: yeozy@nus.edu.sg
Requires-Python: >=3.8
Requires-Dist: numpy
Requires-Dist: scikit-learn
Requires-Dist: matplotlib
Requires-Dist: umap-learn
Dynamic: author
Dynamic: author-email
Dynamic: description
Dynamic: description-content-type
Dynamic: requires-dist
Dynamic: requires-python
Dynamic: summary
